kivy_glow/__init__.py
kivy_glow/app.py
kivy_glow/colors.py
kivy_glow/factory_registers.py
kivy_glow/fonts.py
kivy_glow/icons.py
kivy_glow/theme.py
kivy_glow/assets/fonts/Montserrat-Black.ttf
kivy_glow/assets/fonts/Montserrat-BlackItalic.ttf
kivy_glow/assets/fonts/Montserrat-Bold.ttf
kivy_glow/assets/fonts/Montserrat-BoldItalic.ttf
kivy_glow/assets/fonts/Montserrat-ExtraBold.ttf
kivy_glow/assets/fonts/Montserrat-ExtraBoldItalic.ttf
kivy_glow/assets/fonts/Montserrat-ExtraLight.ttf
kivy_glow/assets/fonts/Montserrat-ExtraLightItalic.ttf
kivy_glow/assets/fonts/Montserrat-Italic.ttf
kivy_glow/assets/fonts/Montserrat-Light.ttf
kivy_glow/assets/fonts/Montserrat-LightItalic.ttf
kivy_glow/assets/fonts/Montserrat-Medium.ttf
kivy_glow/assets/fonts/Montserrat-MediumItalic.ttf
kivy_glow/assets/fonts/Montserrat-Regular.ttf
kivy_glow/assets/fonts/Montserrat-SemiBold.ttf
kivy_glow/assets/fonts/Montserrat-SemiBoldItalic.ttf
kivy_glow/assets/fonts/Montserrat-Thin.ttf
kivy_glow/assets/fonts/Montserrat-ThinItalic.ttf
kivy_glow/assets/fonts/materialdesignicons.ttf
kivy_glow/assets/fonts/MaterialIcons/Outlined/MaterialIconsOutlined-Bold.ttf
kivy_glow/assets/fonts/MaterialIcons/Outlined/MaterialIconsOutlined-ExtraLight.ttf
kivy_glow/assets/fonts/MaterialIcons/Outlined/MaterialIconsOutlined-Light.ttf
kivy_glow/assets/fonts/MaterialIcons/Outlined/MaterialIconsOutlined-Medium.ttf
kivy_glow/assets/fonts/MaterialIcons/Outlined/MaterialIconsOutlined-Regular.ttf
kivy_glow/assets/fonts/MaterialIcons/Outlined/MaterialIconsOutlined-SemiBold.ttf
kivy_glow/assets/fonts/MaterialIcons/Outlined/MaterialIconsOutlined-Thin.ttf
kivy_glow/assets/fonts/MaterialIcons/Outlined/MaterialIconsOutlined_Filled-Bold.ttf
kivy_glow/assets/fonts/MaterialIcons/Outlined/MaterialIconsOutlined_Filled-ExtraLight.ttf
kivy_glow/assets/fonts/MaterialIcons/Outlined/MaterialIconsOutlined_Filled-Light.ttf
kivy_glow/assets/fonts/MaterialIcons/Outlined/MaterialIconsOutlined_Filled-Medium.ttf
kivy_glow-1.0.6.dist-info/LICENSE
kivy_glow-1.0.6.dist-info/METADATA
kivy_glow-1.0.6.dist-info/WHEEL
kivy_glow-1.0.6.dist-info/top_level.txt
kivy_glow-1.0.6.dist-info/RECORD
